LICENSE
MANIFEST.in
README.md
pyproject.toml
setup.py
src/braindynamics_starprotocol/__init__.py
src/braindynamics_starprotocol/trialbraindata.py
src/braindynamics_starprotocol.egg-info/PKG-INFO
src/braindynamics_starprotocol.egg-info/SOURCES.txt
src/braindynamics_starprotocol.egg-info/dependency_links.txt
src/braindynamics_starprotocol.egg-info/requires.txt
src/braindynamics_starprotocol.egg-info/top_level.txt
src/braindynamics_starprotocol/network/__init__.py
src/braindynamics_starprotocol/network/compare.py
src/braindynamics_starprotocol/network/networkdata.py
src/braindynamics_starprotocol/network/plot.py
src/braindynamics_starprotocol/network/sort.py
src/braindynamics_starprotocol/sca/__init__.py
src/braindynamics_starprotocol/sca/crosscorrelogram.py
src/braindynamics_starprotocol/sca/sca_cy.c
src/braindynamics_starprotocol/sca/sca_cy.pyx