Metadata-Version: 2.4
Name: braindynamics_starprotocol
Version: 1.0.3
Summary: Functional brain network analysis protocol developed by Varga et al., 2024
Author-email: vlewir <levente.varga@ubbcluj.ro>, bpentek <balazs.pentek@ubbcluj.ro>
Project-URL: Homepage, https://github.com/vlewir/BrainDynamics_STARProtocols
Project-URL: Issues, https://github.com/vlewir/BrainDynamics_STARProtocols/issues
Classifier: Programming Language :: Python :: 3
Classifier: License :: OSI Approved :: MIT License
Classifier: Operating System :: OS Independent
Requires-Python: >=3.12
License-File: LICENSE
Requires-Dist: igraph>=0.11.6
Requires-Dist: pandas>=2.2.2
Requires-Dist: scipy>=1.14.0
Requires-Dist: matplotlib>=3.9.2
Requires-Dist: cliffs_delta>=1.0.0
Dynamic: license-file
